simplistic/__init__.py
simplistic/exceptions.py
simplistic/trait.py
simplistic-0.2.0a0.dist-info/LICENSE
simplistic-0.2.0a0.dist-info/METADATA
simplistic-0.2.0a0.dist-info/WHEEL
simplistic-0.2.0a0.dist-info/top_level.txt
simplistic-0.2.0a0.dist-info/RECORD
