Metadata-Version: 2.1
Name: simplistic
Version: 0.2.0a0
Summary: A base class for wrapping CLI commands.
Author-email: "Jesse C. Sealand" <jesse.sealand@outlook.com>
License: MIT License
Project-URL: Homepage, https://github.com/jesse-sealand/simplistic
Project-URL: Bug Tracker, https://github.com/jesse-sealand/simplistic/issues
Keywords: python3,python,cli,cli wrapper
Classifier: Programming Language :: Python :: 3
Classifier: License :: OSI Approved :: MIT License
Classifier: Operating System :: OS Independent
Requires-Python: >=3.8
License-File: LICENSE
